sirnaforge/__init__.py
sirnaforge/cli.py
sirnaforge/modifications.py
sirnaforge/workflow.py
sirnaforge/workflow_variant.py
sirnaforge/config/__init__.py
sirnaforge/config/reference_policy.py
sirnaforge/core/__init__.py
sirnaforge/core/design.py
sirnaforge/core/off_target.py
sirnaforge/core/thermodynamics.py
sirnaforge/data/__init__.py
sirnaforge/data/base.py
sirnaforge/data/gene_search.py
sirnaforge/data/mirna_manager.py
sirnaforge/data/orf_analysis.py
sirnaforge/data/reference_manager.py
sirnaforge/data/species_registry.py
sirnaforge/data/transcript_annotation.py
sirnaforge/data/transcriptome_filter.py
sirnaforge/data/transcriptome_manager.py
sirnaforge/data/variant_cache.py
sirnaforge/data/variant_helpers.py
sirnaforge/data/variant_resolver.py
sirnaforge/models/__init__.py
sirnaforge/models/modifications.py
sirnaforge/models/off_target.py
sirnaforge/models/schemas.py
sirnaforge/models/sirna.py
sirnaforge/models/transcript_annotation.py
sirnaforge/models/variant.py
sirnaforge/pipeline/__init__.py
sirnaforge/pipeline/nextflow_cli.py
sirnaforge/pipeline/nextflow/__init__.py
sirnaforge/pipeline/nextflow/config.py
sirnaforge/pipeline/nextflow/runner.py
sirnaforge/pipeline/nextflow/workflows/main.nf
sirnaforge/pipeline/nextflow/workflows/nextflow.config
sirnaforge/pipeline/nextflow/workflows/modules/local/aggregate_results.nf
sirnaforge/pipeline/nextflow/workflows/modules/local/build_bwa_index.nf
sirnaforge/pipeline/nextflow/workflows/modules/local/mirna_seed_analysis.nf
sirnaforge/pipeline/nextflow/workflows/modules/local/offtarget_analysis.nf
sirnaforge/pipeline/nextflow/workflows/subworkflows/local/sirna_offtarget_analysis.nf
sirnaforge/pipeline/resources/__init__.py
sirnaforge/pipeline/resources/genomes.yaml
sirnaforge/pipeline/resources/resources.py
sirnaforge/pipeline/resources/test_data/genomes.yaml
sirnaforge/pipeline/resources/test_data/test_candidates.fasta
sirnaforge/pipeline/resources/test_data/test_mirna_seeds.fasta
sirnaforge-0.4.1.dist-info/METADATA
sirnaforge-0.4.1.dist-info/WHEEL
sirnaforge-0.4.1.dist-info/entry_points.txt
sirnaforge-0.4.1.dist-info/licenses/LICENSE
sirnaforge-0.4.1.dist-info/RECORD
