Metadata-Version: 2.4
Name: sirnaforge
Version: 0.4.1
Summary: siRNAforge - Multi-species gene to siRNA design, off-target prediction, and ranking. Comprehensive siRNA design toolkit for gene silencing
Project-URL: Changelog, https://github.com/austin-s-h/sirnaforge/blob/main/CHANGELOG.md
Project-URL: Documentation, https://austin-s-h.github.io/sirnaforge
Project-URL: Homepage, https://github.com/austin-s-h/sirnaforge
Project-URL: Issues, https://github.com/austin-s-h/sirnaforge/issues
Project-URL: Repository, https://github.com/austin-s-h/sirnaforge
Author-email: "Austin S. Hovland." <austin@sansterbioanalytics.com>
License: MIT License
License-File: LICENSE
Keywords: bioinformatics,computational-biology,gene-silencing,rna-interference,sirna
Classifier: Development Status :: 3 - Alpha
Classifier: Intended Audience :: Science/Research
Classifier: License :: OSI Approved :: MIT License
Classifier: Operating System :: OS Independent
Classifier: Programming Language :: Python :: 3
Classifier: Programming Language :: Python :: 3.9
Classifier: Programming Language :: Python :: 3.10
Classifier: Programming Language :: Python :: 3.11
Classifier: Programming Language :: Python :: 3.12
Classifier: Topic :: Scientific/Engineering :: Bio-Informatics
Requires-Python: <3.13,>=3.10
Requires-Dist: aiohttp>=3.12.0
Requires-Dist: biopython>=1.84
Requires-Dist: click>=8.0.0
Requires-Dist: httpx>=0.28.0
Requires-Dist: nextflow>=25.04.0
Requires-Dist: numpy>=1.26.0
Requires-Dist: pandas>=2.3.0
Requires-Dist: pandera>=0.26.0
Requires-Dist: psutil>=6.0.0
Requires-Dist: pyarrow>=18.0.0
Requires-Dist: pydantic>=2.11.0
Requires-Dist: pysam>=0.23.0
Requires-Dist: requests>=2.32.0
Requires-Dist: rich>=14.0.0
Requires-Dist: typer>=0.17.0
Requires-Dist: viennarna>=2.7.0
